<?xml version="1.0" encoding="utf-8"?>
<Window showshadow="true" shadowimage="shadow_bkg.png" shadowcorner="7,7,7,7">
<Font name="微软雅黑" size="12" bold="false" default="true" />
<Font name="微软雅黑" size="12" bold="true"/>

<!-- Menu标签的属性要通过Default来定义，为了让下级菜单也能拥有同样的外观 -->
<Default name="Menu" value="inset=&quot;2,2,2,2&quot; itemtextpadding=&quot;30,0,0,0&quot; bkimage=&quot;file='Menu\menu_bkg.png' source='7,7,125,25' corner='26,5,5,5'&quot; itemselectedbkcolor=&quot;0xFF338ACA&quot;" />

<!-- ExplandIcon属性定义了下级菜单的小图标的样子 -->
<Default name="ExplandIcon" value="Menu\menu_arrow.png" />
<Menu>
	<MenuElement name="MENU_CUT" text="开始语音通话" height="22" />
	<MenuElement name="MENU_INPUT_COPY" text="发起多人语音" height="22" />
	<MenuElement name="MENU_PASTE" text="语音设置" height="22" />
	<MenuElement name="MENU_PASTE" text="语音测试向导" height="22" />
	<MenuElement name="MENU_PASTE" text="发送语音消息" height="22" />
</Menu>
</Window>